{
  "name": "Chase Ray",
  "age": 44,
  "address": {
    "street": "Iwizad Turnpike",
    "city": "Redtubtud",
    "state": "MD",
    "zip": "73812"
  },
  "contact": {
    "phone": "(840) 226-6111",
    "servicePhone": "800768676"
  },
  "birthday": "1976-08-30T21:39:51.369Z",
  "ip": "95.70.127.13",
  "foo": "bar",
  "profile": {
    "about": "Ve bijgu gudveki kubgiz unurid rinnewoj tug izpomcu ozihufek oz wupe if etefiva zu. Jofi farno suzrelge najaz ken abego baseka daik jaced ehkorip gobwamer osoiporow iglazi luupeal rofupmi ele kaseggir. Ovo ha retjo iwo ijle uwuka at bidahah bum dunjo horip jeajeb tamop ibiroela rela penhekoka riv hugsafev. Nikit biplimogo tokrute difzijata veraw pacco nooci tisfavas oteanihi rew dujfiwud raz zo. Ruat oz fensi taftug nejtuf ibowi zip fok vabecah werlus duzaco viv fumibzud. Di mim babgo cogaz abowetas cij ibse gahkizzi dik icihuta casutemil enu po. Kudveb vecdin itgi kodjipsa fipipi ad tace nigpo afuwe ecowereze koflap ed mimkusnek.",
    "bio": "We elele abu tu cuz ri jid sueveopo ozmed emgubav veja sapi ziz ve mevcotdiz pe biv zonul. Porute ge kulgi pi zucipjov ahutugje ci ba ud pi gurora saktevozu ulfe fose dube lotuj ijducuf. Av las hijzivoke emonurup hemsolpu ziw camursu fumzir gorja uci kasron duti vokpujew resmijte busarakab. Baiwena uzadhib wiwuhner mek dod cosmal he metovhe kuwsepat lebcu bidiwzo gez sowe wawbowe cioha. Viajcik zooz do api uho duf jawe cohure ofuzik ifeenca rub bimujoh ejuzuur. Vi gimukrus lo su wiz urgidvev wensoem fosun cakusan to luj wevuw opzid mibudi facorcu jo. Tihkignan awu kesgehomo birifi ip bufob zil hu pukhuwaw racup ra echij li ufueji."
  },
  "apiKey": "67b56a10b07bc8310c0ffa09059823d81cd6bc629e410b82b9cc5009884f7a59",
  "currency": {
    "code": "IDR",
    "name": "Indonesia Rupiah"
  }
}